digikalacrawler/__init__.py
digikalacrawler/crawler.py
digikalacrawler-0.0.5.dist-info/METADATA
digikalacrawler-0.0.5.dist-info/WHEEL
digikalacrawler-0.0.5.dist-info/top_level.txt
digikalacrawler-0.0.5.dist-info/RECORD
